ImageD11/fft_index_refac.py
ImageD11/gv_general.py
ImageD11/labelimage.py
ImageD11/correct.py
ImageD11/guicommand.py
ImageD11/unitcell.py
ImageD11/rsv.py
ImageD11/weighted_kde.py
ImageD11/peaksearcher.py
ImageD11/rc_array.py
ImageD11/blobcorrector.py
ImageD11/sym_u.py
ImageD11/peakmerge.py
ImageD11/ImageD11_file_series.py
ImageD11/fetch_data.py
ImageD11/cImageD11.py
ImageD11/__init__.py
ImageD11/cImageD11_docstrings.py
ImageD11/rotdex.py
ImageD11/rsv_mapper.py
ImageD11/symops.py
ImageD11/grain.py
ImageD11/ImageD11options.py
ImageD11/stress.py
ImageD11/write_graindex_gv.py
ImageD11/_cImageD11.cpython-38-darwin.so
ImageD11/transformer.py
ImageD11/columnfile.py
ImageD11/transform.py
ImageD11/ImageD11_thread.py
ImageD11/parameters.py
ImageD11/refinegrains.py
ImageD11/simplex.py
ImageD11/license.py
ImageD11/grid_index_parallel.py
ImageD11/frelon_peaksearch.py
ImageD11/sparseframe.py
ImageD11/indexing.py
ImageD11/saintraw.py
ImageD11/compute_fazit.py
ImageD11/lattice_reduction.py
ImageD11/scale.py
ImageD11/finite_strain.py
ImageD11/peakselect.py
ImageD11/nbGui/test_gui_fit.ipynb
ImageD11/nbGui/plot3d.py
ImageD11/nbGui/segmenter_gui_utils.py
ImageD11/nbGui/draw_mask.py
ImageD11/nbGui/segmenter_gui.py
ImageD11/nbGui/__init__.py
ImageD11/nbGui/install_ImageD11_from_git.py
ImageD11/nbGui/fit_geometry.py
ImageD11/nbGui/nb_utils.py
ImageD11/nbGui/interactive_peakselect.py
ImageD11/nbGui/plot3d.ipynb
ImageD11/nbGui/S3DXRD/run_astra_recon.py
ImageD11/nbGui/S3DXRD/tomo_2_map.ipynb
ImageD11/nbGui/S3DXRD/5_combine_phases.ipynb
ImageD11/nbGui/S3DXRD/inspect_tensormap.ipynb
ImageD11/nbGui/S3DXRD/pbp_2_visualise.ipynb
ImageD11/nbGui/S3DXRD/incorporate_strains.ipynb
ImageD11/nbGui/S3DXRD/tomo_2_map_minor_phase.ipynb
ImageD11/nbGui/S3DXRD/__init__.py
ImageD11/nbGui/S3DXRD/pbp_1_indexing.ipynb
ImageD11/nbGui/S3DXRD/run_pbp_recon_chunk.py
ImageD11/nbGui/S3DXRD/pbp_3_refinement.ipynb
imaged11-2.1.3.dist-info/RECORD
imaged11-2.1.3.dist-info/LICENSE
imaged11-2.1.3.dist-info/WHEEL
imaged11-2.1.3.dist-info/top_level.txt
imaged11-2.1.3.dist-info/METADATA
