Metadata-Version: 2.1
Name: ImageD11
Version: 2.1.3
Summary: ImageD11
Home-page: http://github.com/jonwright/ImageD11
Author: Jon Wright
Author-email: wright@esrf.fr
License: GPL
License-File: LICENSE
Requires-Dist: numpy
Requires-Dist: setuptools
Requires-Dist: xfab>=0.0.4
Requires-Dist: matplotlib
Requires-Dist: pyopengltk
Requires-Dist: scipy
Requires-Dist: h5py
Requires-Dist: pyyaml
Requires-Dist: pytest
Requires-Dist: bslz4-to-sparse
Requires-Dist: fast-histogram
Requires-Dist: scikit-image
Requires-Dist: tqdm
Requires-Dist: pyopengl==3.1.7; python_version < "3"
Requires-Dist: hdf5plugin==1.4.1; python_version < "3"
Requires-Dist: numba==0.46.0; python_version < "3"
Requires-Dist: llvmlite==0.30.0; python_version < "3"
Requires-Dist: fabio==0.2.2; python_version < "3" and sys_platform == "win32"
Requires-Dist: numba>=0.63.0b1; python_version == "3.14"
Requires-Dist: pyopengl; python_version >= "3"
Requires-Dist: hdf5plugin; python_version >= "3"
Requires-Dist: threadpoolctl; python_version >= "3"
Requires-Dist: orix; python_version >= "3"
Requires-Dist: diffpy.structure; python_version >= "3"
Requires-Dist: numba; python_version >= "3" and python_version < "3.14"
Requires-Dist: fabio; python_version >= "3" or sys_platform != "win32"
Provides-Extra: full
Requires-Dist: papermill; extra == "full"
Requires-Dist: pillow; extra == "full"
Requires-Dist: lmfit; extra == "full"
Requires-Dist: sympy; extra == "full"
Requires-Dist: pandas; extra == "full"
Requires-Dist: numexpr<=2.7.0; python_version < "3" and extra == "full"
Requires-Dist: ipywidgets; python_version >= "3" and extra == "full"
Requires-Dist: pyopencl; python_version >= "3" and extra == "full"
Requires-Dist: pyFAI; python_version >= "3" and extra == "full"
Requires-Dist: silx[full]; python_version >= "3" and extra == "full"
Provides-Extra: rare
Requires-Dist: FitAllB; extra == "rare"
Requires-Dist: minuit; extra == "rare"
Requires-Dist: PyTango; extra == "rare"
Requires-Dist: PyMca5; extra == "rare"
